README.md
setup.cfg
setup.py
bin/__init__.py
bin/run.py
pip_facades_sample_python/__init__.py
pip_facades_sample_python.egg-info/PKG-INFO
pip_facades_sample_python.egg-info/SOURCES.txt
pip_facades_sample_python.egg-info/dependency_links.txt
pip_facades_sample_python.egg-info/requires.txt
pip_facades_sample_python.egg-info/top_level.txt
pip_facades_sample_python.egg-info/zip-safe
pip_facades_sample_python/build/ClientFacadeFactory.py
pip_facades_sample_python/build/FacadeFactory.py
pip_facades_sample_python/build/ServiceFacadeFactory.py
pip_facades_sample_python/build/__init__.py
pip_facades_sample_python/container/FacadeProcess.py
pip_facades_sample_python/container/__init__.py
pip_facades_sample_python/operations/__init__.py
pip_facades_sample_python/operations/version1/BeaconsOperations.py
pip_facades_sample_python/operations/version1/__init__.py
pip_facades_sample_python/services/__init__.py
pip_facades_sample_python/services/version1/AuthorizerV1.py
pip_facades_sample_python/services/version1/FacadeServiceV1.py
pip_facades_sample_python/services/version1/__init__.py
test/fixtures/ReferencesTest.py
test/fixtures/RestClientTest.py
test/fixtures/__init__.py
test/operations/__init__.py
test/operations/test_BeaconsRoutes.py